noteforge/__init__.py
noteforge/data/__init__.py
noteforge/data/alterations/__init__.py
noteforge/data/alterations/mappings.py
noteforge/data/alterations/validation_handlers.py
noteforge/data/freqs/__init__.py
noteforge/data/freqs/get_handlers.py
noteforge/data/freqs/mappings.py
noteforge/data/freqs/validation_handlers.py
noteforge/data/intervals/__init__.py
noteforge/data/intervals/mappings.py
noteforge/data/intervals/validation_handlers.py
noteforge/data/note/__init__.py
noteforge/data/note/mappings.py
noteforge/data/note/validation_handlers.py
noteforge/structures/__init__.py
noteforge/structures/harmonicMap/harmonicMap.py
noteforge/structures/interval/__init__.py
noteforge/structures/interval/interval.py
noteforge/structures/interval/interval_getters.py
noteforge/structures/interval/transposers.py
noteforge/structures/note/__init__.py
noteforge/structures/note/morphers.py
noteforge/structures/note/note.py
noteforge-0.0.5.dist-info/METADATA
noteforge-0.0.5.dist-info/WHEEL
noteforge-0.0.5.dist-info/RECORD
