Metadata-Version: 2.4
Name: noteforge
Version: 0.0.5
Summary: A Python library for implementing music theory in data structures, facilitating the management of relationships between notes and the retrieval of specific information about them.
Project-URL: Homepage, https://github.com/radras44/NoteForge
Project-URL: Issues, https://github.com/radras44/NoteForge/issues
Author-email: Radras44 <radrastreyarch@gmail.com>
License-Expression: MIT
Classifier: Operating System :: OS Independent
Classifier: Programming Language :: Python :: 3
Requires-Python: >=3.9
